.coveragerc
.editorconfig
.gitignore
.travis.yml
LICENSE
README.md
pyproject.toml
requirements.txt
requirements_dev.txt
setup.cfg
setup.py
.github/workflows/python-publish.yml
democritus_timezones/__init__.py
democritus_timezones/democritus_timezones.py
democritus_timezones/democritus_timezones_temp_utils.py
democritus_timezones.egg-info/PKG-INFO
democritus_timezones.egg-info/SOURCES.txt
democritus_timezones.egg-info/dependency_links.txt
democritus_timezones.egg-info/requires.txt
democritus_timezones.egg-info/top_level.txt
democritus_timezones.egg-info/zip-safe
tests/__init__.py
tests/test_democritus_timezones.py